{
  "indexes": [
    {
      "collectionGroup": "patterns",
      "queryScope": "COLLECTION",
      "fields": [
        { "fieldPath": "isPublic", "order": "ASCENDING" },
        { "fieldPath": "likes", "order": "DESCENDING" },
        { "fieldPath": "createdAt", "order": "DESCENDING" }
      ]
    },
    {
      "collectionGroup": "patterns",
      "queryScope": "COLLECTION",
      "fields": [
        { "fieldPath": "isPublic", "order": "ASCENDING" },
        { "fieldPath": "expressionType", "order": "ASCENDING" },
        { "fieldPath": "createdAt", "order": "DESCENDING" }
      ]
    },
    {
      "collectionGroup": "patterns",
      "queryScope": "COLLECTION",
      "fields": [
        { "fieldPath": "isPublic", "order": "ASCENDING" },
        { "fieldPath": "deviceType", "order": "ASCENDING" },
        { "fieldPath": "likes", "order": "DESCENDING" }
      ]
    },
    {
      "collectionGroup": "patterns",
      "queryScope": "COLLECTION",
      "fields": [
        { "fieldPath": "isPublic", "order": "ASCENDING" },
        { "fieldPath": "downloads", "order": "DESCENDING" },
        { "fieldPath": "createdAt", "order": "DESCENDING" }
      ]
    }
  ],
  "fieldOverrides": []
}
